compare_df
