Metadata-Version: 2.1
Name: compare-df
Version: 0.5
Summary: A collection of function which can be used to compare two dataframes.
Home-page: https://github.com/Sanyam15/compare_df
Author: Sanyam Gupta
Author-email: sanyam15111@gmail.com
License: MIT
Download-URL: https://github.com/Sanyam15/compare_df/archive/v0.2.tar.gz
Keywords: Machine Learning,Comparison,Excel,CSV,Pandas,DataFrame,Validation
Platform: UNKNOWN
Classifier: Development Status :: 4 - Beta
Classifier: Intended Audience :: Developers
Classifier: Topic :: Software Development :: Build Tools
Classifier: License :: OSI Approved :: MIT License
Classifier: Programming Language :: Python :: 3
Classifier: Programming Language :: Python :: 3.4
Classifier: Programming Language :: Python :: 3.5
Classifier: Programming Language :: Python :: 3.6
Classifier: Programming Language :: Python :: 3.7
Classifier: Programming Language :: Python :: 3.8
